<?xml version="1.0" encoding="UTF-8"?><functionMetadata xmlns="http://www.businessobjects.com/cal/metadata" xmlns:metadata="http://www.businessobjects.com/cal/metadata" xmlns:xsi="http://www.w3.org/2001/XMLSchema-instance" xsi:schemaLocation="http://www.businessobjects.com/cal/metadata file:metadata.xsd"><functionalAgentMetadata><scopedEntityMetadata><featureMetadata><resourceName xmlns="http://www.businessobjects.com/cal/workspace"><type><![CDATA[LocalizedResourceName]]></type><featureName><type><![CDATA[FUNCTION]]></type><name><![CDATA[Cal.Core.Prelude.downFrom]]></name></featureName></resourceName><displayName/><version/><author><![CDATA[Business Objects]]></author><shortDescription/><longDescription><![CDATA[Creates the infinite list [n, n-1, n-2, n-3, ...] from a given number.]]></longDescription><modificationDate><![CDATA[2006-05-08T14:51:04]]></modificationDate><creationDate><![CDATA[2003-12-02T09:57:28]]></creationDate><expertFeature><![CDATA[false]]></expertFeature><hiddenFeature><![CDATA[false]]></hiddenFeature><preferredFeature><![CDATA[false]]></preferredFeature><attributes/><relatedFeatures/></featureMetadata></scopedEntityMetadata><categories/><arguments><argumentMetadata><featureMetadata><resourceName xmlns="http://www.businessobjects.com/cal/workspace"><type><![CDATA[LocalizedResourceName]]></type><featureName><type><![CDATA[ARGUMENT]]></type><name><![CDATA[0]]></name></featureName></resourceName><displayName><![CDATA[start]]></displayName><version/><author/><shortDescription><![CDATA[The number to begin the infinite list.]]></shortDescription><longDescription/><modificationDate><![CDATA[2006-05-08T14:51:04]]></modificationDate><creationDate><![CDATA[2003-12-02T09:57:28]]></creationDate><expertFeature><![CDATA[false]]></expertFeature><hiddenFeature><![CDATA[false]]></hiddenFeature><preferredFeature><![CDATA[false]]></preferredFeature><attributes/><relatedFeatures/></featureMetadata><defaultValuesOnly><![CDATA[false]]></defaultValuesOnly><defaultValuesExpression><expression/></defaultValuesExpression><promptingTextExpression><expression/></promptingTextExpression></argumentMetadata></arguments><examples><example><description><![CDATA[Generate a list of numbers that counts down from 4 and return the first 10 elements.]]></description><evaluateExpression><![CDATA[true]]></evaluateExpression><expression><moduleContext><![CDATA[Cal.Core.Prelude]]></moduleContext><calExpressionText><![CDATA[take 10 (downFrom 4.0)]]></calExpressionText><qualifiedCalExpressionText><![CDATA[take 10 (downFrom 4.0)]]></qualifiedCalExpressionText><qualificationMap><functions><mapping module="Cal.Core.Prelude" unqualifiedName="downFrom"/><mapping module="Cal.Core.Prelude" unqualifiedName="take"/></functions><constructors/><types/><classes/></qualificationMap></expression></example></examples></functionalAgentMetadata><returnValue/></functionMetadata>