<?xml version="1.0" encoding="UTF-8"?><dataConstructorMetadata xmlns="http://www.businessobjects.com/cal/metadata" xmlns:metadata="http://www.businessobjects.com/cal/metadata" xmlns:xsi="http://www.w3.org/2001/XMLSchema-instance" xsi:schemaLocation="http://www.businessobjects.com/cal/metadata file:metadata.xsd"><functionalAgentMetadata><scopedEntityMetadata><featureMetadata><resourceName xmlns="http://www.businessobjects.com/cal/workspace"><type><![CDATA[LocalizedResourceName]]></type><featureName><type><![CDATA[DATA_CONSTRUCTOR]]></type><name><![CDATA[Cal.Samples.Plot.Glyph_X]]></name></featureName></resourceName><displayName/><version><![CDATA[1.0.0]]></version><author><![CDATA[Business Objects]]></author><shortDescription/><longDescription><![CDATA[The X (diagonal cross) glyph style.]]></longDescription><modificationDate><![CDATA[2006-05-08T14:51:13]]></modificationDate><creationDate><![CDATA[2003-12-02T09:57:31]]></creationDate><expertFeature><![CDATA[false]]></expertFeature><hiddenFeature><![CDATA[false]]></hiddenFeature><preferredFeature><![CDATA[false]]></preferredFeature><attributes/><relatedFeatures/></featureMetadata></scopedEntityMetadata><categories/><arguments/><examples/></functionalAgentMetadata></dataConstructorMetadata>