<?xml version="1.0" encoding="UTF-8"?><classMethodMetadata xmlns="http://www.businessobjects.com/cal/metadata" xmlns:metadata="http://www.businessobjects.com/cal/metadata" xmlns:xsi="http://www.w3.org/2001/XMLSchema-instance" xsi:schemaLocation="http://www.businessobjects.com/cal/metadata file:metadata.xsd"><functionalAgentMetadata><scopedEntityMetadata><featureMetadata><resourceName xmlns="http://www.businessobjects.com/cal/workspace"><type><![CDATA[LocalizedResourceName]]></type><featureName><type><![CDATA[CLASS_METHOD]]></type><name><![CDATA[Cal.Core.Prelude.compare]]></name></featureName></resourceName><displayName/><version/><author><![CDATA[Business Objects]]></author><shortDescription/><longDescription><![CDATA[Returns an Ordering based on how one value compares to a second.

LT is returned when the first value is less than the second.
EQ is returned when the 2 values are equal.
GT is returned when the first value is greater than the second.]]></longDescription><modificationDate><![CDATA[2007-11-02T16:13:19]]></modificationDate><creationDate><![CDATA[2003-12-02T09:57:29]]></creationDate><expertFeature><![CDATA[false]]></expertFeature><hiddenFeature><![CDATA[false]]></hiddenFeature><preferredFeature><![CDATA[false]]></preferredFeature><attributes/><relatedFeatures/></featureMetadata></scopedEntityMetadata><categories/><arguments><argumentMetadata><featureMetadata><resourceName xmlns="http://www.businessobjects.com/cal/workspace"><type><![CDATA[LocalizedResourceName]]></type><featureName><type><![CDATA[ARGUMENT]]></type><name><![CDATA[0]]></name></featureName></resourceName><displayName><![CDATA[value1]]></displayName><version/><author/><shortDescription><![CDATA[The first value.]]></shortDescription><longDescription/><modificationDate><![CDATA[2007-11-02T16:13:19]]></modificationDate><creationDate><![CDATA[2003-12-02T09:57:29]]></creationDate><expertFeature><![CDATA[false]]></expertFeature><hiddenFeature><![CDATA[false]]></hiddenFeature><preferredFeature><![CDATA[false]]></preferredFeature><attributes/><relatedFeatures/></featureMetadata><defaultValuesOnly><![CDATA[false]]></defaultValuesOnly><defaultValuesExpression><expression/></defaultValuesExpression><promptingTextExpression><expression/></promptingTextExpression></argumentMetadata><argumentMetadata><featureMetadata><resourceName xmlns="http://www.businessobjects.com/cal/workspace"><type><![CDATA[LocalizedResourceName]]></type><featureName><type><![CDATA[ARGUMENT]]></type><name><![CDATA[1]]></name></featureName></resourceName><displayName><![CDATA[value2]]></displayName><version/><author/><shortDescription><![CDATA[The second value.]]></shortDescription><longDescription/><modificationDate><![CDATA[2007-11-02T16:13:19]]></modificationDate><creationDate><![CDATA[2003-12-02T09:57:29]]></creationDate><expertFeature><![CDATA[false]]></expertFeature><hiddenFeature><![CDATA[false]]></hiddenFeature><preferredFeature><![CDATA[false]]></preferredFeature><attributes/><relatedFeatures/></featureMetadata><defaultValuesOnly><![CDATA[false]]></defaultValuesOnly><defaultValuesExpression><expression/></defaultValuesExpression><promptingTextExpression><expression/></promptingTextExpression></argumentMetadata></arguments><examples><example><description/><evaluateExpression><![CDATA[true]]></evaluateExpression><expression><moduleContext><![CDATA[Cal.Core.Prelude]]></moduleContext><calExpressionText><![CDATA[compare 1.0 2.0]]></calExpressionText><qualifiedCalExpressionText><![CDATA[compare 1.0 2.0]]></qualifiedCalExpressionText><qualificationMap><functions><mapping module="Cal.Core.Prelude" unqualifiedName="compare"/></functions><constructors/><types/><classes/></qualificationMap></expression></example><example><description/><evaluateExpression><![CDATA[true]]></evaluateExpression><expression><moduleContext><![CDATA[Cal.Core.Prelude]]></moduleContext><calExpressionText><![CDATA[compare 'a' 'a']]></calExpressionText><qualifiedCalExpressionText><![CDATA[compare 'a' 'a']]></qualifiedCalExpressionText><qualificationMap><functions><mapping module="Cal.Core.Prelude" unqualifiedName="compare"/></functions><constructors/><types/><classes/></qualificationMap></expression></example><example><description/><evaluateExpression><![CDATA[true]]></evaluateExpression><expression><moduleContext><![CDATA[Cal.Core.Prelude]]></moduleContext><calExpressionText><![CDATA[compare 'd' 'a']]></calExpressionText><qualifiedCalExpressionText><![CDATA[compare 'd' 'a']]></qualifiedCalExpressionText><qualificationMap><functions><mapping module="Cal.Core.Prelude" unqualifiedName="compare"/></functions><constructors/><types/><classes/></qualificationMap></expression></example></examples></functionalAgentMetadata><returnValue/></classMethodMetadata>